{
  "graph_id": "AadlProjects_smartparking_vehbasesafe_impl_1.aaxl2",
  "ra_name": "Smart Parking System Reference Architecture",
  "num_nodes": 10,
  "num_edges": 5,
  "evaluated_nodes": 10,
  "correct_predictions": 3,
  "accuracy": 0.3,
  "predictions": [
    {
      "node_id": "comp_system",
      "graph_node_id": "SYSTEM::AadlProjects_smartparking_vehbasesafe_impl_1.aaxl2",
      "node_name": "SYSTEM",
      "category": "system",
      "classifier": "",
      "predicted_ra_id": "comp.business",
      "predicted_ra_name": "Business_Logic_Layer",
      "prediction_score": 0.593744,
      "top_5_candidates": [
        {
          "ra_id": "comp.business",
          "ra_name": "Business_Logic_Layer",
          "score": 0.593744
        },
        {
          "ra_id": "comp.security",
          "ra_name": "Security",
          "score": 0.593744
        },
        {
          "ra_id": "comp.presentation",
          "ra_name": "Presentation_Layer",
          "score": 0.525144
        },
        {
          "ra_id": "comp.data",
          "ra_name": "Data_Management_Layer",
          "score": 0.525144
        }
      ],
      "ground_truth": [
        {
          "ra_name": "Business_Logic_Layer",
          "ra_id": "comp.business",
          "confidence": 1,
          "source_row": 0,
          "aadl_graph_id": "AadlProjects_smartparking_vehbasesafe_impl_1.aaxl2",
          "match_mode": "global_fallback"
        },
        {
          "ra_name": "Business_Logic_Layer",
          "ra_id": "comp.business",
          "confidence": 1,
          "source_row": 104,
          "aadl_graph_id": "AadlProjects_smartparking_vehbasesafe_impl_1.aaxl2",
          "match_mode": "global_fallback"
        },
        {
          "ra_name": "Business_Logic_Layer",
          "ra_id": "comp.business",
          "confidence": 1,
          "source_row": 105,
          "aadl_graph_id": "AadlProjects_smartparking_vehbasesafe_impl_1.aaxl2",
          "match_mode": "global_fallback"
        },
        {
          "ra_name": "Business_Logic_Layer",
          "ra_id": "comp.business",
          "confidence": 1,
          "source_row": 111,
          "aadl_graph_id": "AadlProjects_smartparking_vehbasesafe_impl_1.aaxl2",
          "match_mode": "global_fallback"
        },
        {
          "ra_name": "Business_Logic_Layer",
          "ra_id": "comp.business",
          "confidence": 1,
          "source_row": 116,
          "aadl_graph_id": "AadlProjects_smartparking_vehbasesafe_impl_1.aaxl2",
          "match_mode": "global_fallback"
        },
        {
          "ra_name": "Business_Logic_Layer",
          "ra_id": "comp.business",
          "confidence": 1,
          "source_row": 117,
          "aadl_graph_id": "AadlProjects_smartparking_vehbasesafe_impl_1.aaxl2",
          "match_mode": "global_fallback"
        },
        {
          "ra_name": "Business_Logic_Layer",
          "ra_id": "comp.business",
          "confidence": 1,
          "source_row": 130,
          "aadl_graph_id": "AadlProjects_smartparking_vehbasesafe_impl_1.aaxl2",
          "match_mode": "global_fallback"
        },
        {
          "ra_name": "Business_Logic_Layer",
          "ra_id": "comp.business",
          "confidence": 1,
          "source_row": 140,
          "aadl_graph_id": "AadlProjects_smartparking_vehbasesafe_impl_1.aaxl2",
          "match_mode": "global_fallback"
        },
        {
          "ra_name": "Business_Logic_Layer",
          "ra_id": "comp.business",
          "confidence": 1,
          "source_row": 145,
          "aadl_graph_id": "AadlProjects_smartparking_vehbasesafe_impl_1.aaxl2",
          "match_mode": "global_fallback"
        },
        {
          "ra_name": "Business_Logic_Layer",
          "ra_id": "comp.business",
          "confidence": 1,
          "source_row": 153,
          "aadl_graph_id": "AadlProjects_smartparking_vehbasesafe_impl_1.aaxl2",
          "match_mode": "global_fallback"
        },
        {
          "ra_name": "Business_Logic_Layer",
          "ra_id": "comp.business",
          "confidence": 1,
          "source_row": 156,
          "aadl_graph_id": "AadlProjects_smartparking_vehbasesafe_impl_1.aaxl2",
          "match_mode": "global_fallback"
        },
        {
          "ra_name": "Business_Logic_Layer",
          "ra_id": "comp.business",
          "confidence": 1,
          "source_row": 159,
          "aadl_graph_id": "AadlProjects_smartparking_vehbasesafe_impl_1.aaxl2",
          "match_mode": "global_fallback"
        },
        {
          "ra_name": "Business_Logic_Layer",
          "ra_id": "comp.business",
          "confidence": 1,
          "source_row": 178,
          "aadl_graph_id": "AadlProjects_smartparking_vehbasesafe_impl_1.aaxl2",
          "match_mode": "global_fallback"
        },
        {
          "ra_name": "Business_Logic_Layer",
          "ra_id": "comp.business",
          "confidence": 1,
          "source_row": 181,
          "aadl_graph_id": "AadlProjects_smartparking_vehbasesafe_impl_1.aaxl2",
          "match_mode": "global_fallback"
        },
        {
          "ra_name": "Business_Logic_Layer",
          "ra_id": "comp.business",
          "confidence": 1,
          "source_row": 194,
          "aadl_graph_id": "AadlProjects_smartparking_vehbasesafe_impl_1.aaxl2",
          "match_mode": "global_fallback"
        },
        {
          "ra_name": "Business_Logic_Layer",
          "ra_id": "comp.business",
          "confidence": 1,
          "source_row": 207,
          "aadl_graph_id": "AadlProjects_smartparking_vehbasesafe_impl_1.aaxl2",
          "match_mode": "global_fallback"
        },
        {
          "ra_name": "Business_Logic_Layer",
          "ra_id": "comp.business",
          "confidence": 1,
          "source_row": 214,
          "aadl_graph_id": "AadlProjects_smartparking_vehbasesafe_impl_1.aaxl2",
          "match_mode": "global_fallback"
        },
        {
          "ra_name": "Business_Logic_Layer",
          "ra_id": "comp.business",
          "confidence": 1,
          "source_row": 219,
          "aadl_graph_id": "AadlProjects_smartparking_vehbasesafe_impl_1.aaxl2",
          "match_mode": "global_fallback"
        },
        {
          "ra_name": "Business_Logic_Layer",
          "ra_id": "comp.business",
          "confidence": 1,
          "source_row": 225,
          "aadl_graph_id": "AadlProjects_smartparking_vehbasesafe_impl_1.aaxl2",
          "match_mode": "global_fallback"
        }
      ],
      "is_correct": true
    },
    {
      "node_id": "comp_communicationremote",
      "graph_node_id": "communicationremote::../../github/AadlProjects/smartpark/smartparking.aadl#smartparking.communicationremote.impl",
      "node_name": "communicationremote",
      "category": "process",
      "classifier": "../../github/AadlProjects/smartpark/smartparking.aadl#smartparking.communicationremote.impl",
      "predicted_ra_id": "comp.presentation",
      "predicted_ra_name": "Presentation_Layer",
      "prediction_score": 0.364,
      "top_5_candidates": [
        {
          "ra_id": "comp.presentation",
          "ra_name": "Presentation_Layer",
          "score": 0.364
        },
        {
          "ra_id": "comp.data",
          "ra_name": "Data_Management_Layer",
          "score": 0.364
        },
        {
          "ra_id": "comp.business",
          "ra_name": "Business_Logic_Layer",
          "score": 0.308
        },
        {
          "ra_id": "comp.security",
          "ra_name": "Security",
          "score": 0.308
        }
      ],
      "ground_truth": [
        {
          "ra_name": "Business_Logic_Layer",
          "ra_id": "comp.business",
          "confidence": 1,
          "source_row": 30,
          "aadl_graph_id": "AadlProjects_smartparking_vehbasesafe_impl_1.aaxl2",
          "match_mode": "global_fallback"
        },
        {
          "ra_name": "Business_Logic_Layer",
          "ra_id": "comp.business",
          "confidence": 1,
          "source_row": 131,
          "aadl_graph_id": "AadlProjects_smartparking_vehbasesafe_impl_1.aaxl2",
          "match_mode": "global_fallback"
        },
        {
          "ra_name": "Business_Logic_Layer",
          "ra_id": "comp.business",
          "confidence": 1,
          "source_row": 161,
          "aadl_graph_id": "AadlProjects_smartparking_vehbasesafe_impl_1.aaxl2",
          "match_mode": "global_fallback"
        }
      ],
      "is_correct": false
    },
    {
      "node_id": "comp_deviceidentity",
      "graph_node_id": "deviceidentity::../../github/AadlProjects/smartpark/smartparking.aadl#smartparking.deviceidentity.impl",
      "node_name": "deviceidentity",
      "category": "thread",
      "classifier": "../../github/AadlProjects/smartpark/smartparking.aadl#smartparking.deviceidentity.impl",
      "predicted_ra_id": "comp.presentation",
      "predicted_ra_name": "Presentation_Layer",
      "prediction_score": 0.553667,
      "top_5_candidates": [
        {
          "ra_id": "comp.presentation",
          "ra_name": "Presentation_Layer",
          "score": 0.553667
        },
        {
          "ra_id": "comp.data",
          "ra_name": "Data_Management_Layer",
          "score": 0.553667
        },
        {
          "ra_id": "comp.business",
          "ra_name": "Business_Logic_Layer",
          "score": 0.497667
        },
        {
          "ra_id": "comp.security",
          "ra_name": "Security",
          "score": 0.497667
        }
      ],
      "ground_truth": [
        {
          "ra_name": "Business_Logic_Layer",
          "ra_id": "comp.business",
          "confidence": 1,
          "source_row": 31,
          "aadl_graph_id": "AadlProjects_smartparking_vehbasesafe_impl_1.aaxl2",
          "match_mode": "global_fallback"
        },
        {
          "ra_name": "Business_Logic_Layer",
          "ra_id": "comp.business",
          "confidence": 1,
          "source_row": 132,
          "aadl_graph_id": "AadlProjects_smartparking_vehbasesafe_impl_1.aaxl2",
          "match_mode": "global_fallback"
        },
        {
          "ra_name": "Business_Logic_Layer",
          "ra_id": "comp.business",
          "confidence": 1,
          "source_row": 162,
          "aadl_graph_id": "AadlProjects_smartparking_vehbasesafe_impl_1.aaxl2",
          "match_mode": "global_fallback"
        }
      ],
      "is_correct": false
    },
    {
      "node_id": "comp_driverguidanceinterface",
      "graph_node_id": "driverguidanceinterface::../../github/AadlProjects/smartpark/smartparking.aadl#smartparking.driverguidanceinterface.impl",
      "node_name": "driverguidanceinterface",
      "category": "process",
      "classifier": "../../github/AadlProjects/smartpark/smartparking.aadl#smartparking.driverguidanceinterface.impl",
      "predicted_ra_id": "comp.presentation",
      "predicted_ra_name": "Presentation_Layer",
      "prediction_score": 0.406,
      "top_5_candidates": [
        {
          "ra_id": "comp.presentation",
          "ra_name": "Presentation_Layer",
          "score": 0.406
        },
        {
          "ra_id": "comp.data",
          "ra_name": "Data_Management_Layer",
          "score": 0.406
        },
        {
          "ra_id": "comp.business",
          "ra_name": "Business_Logic_Layer",
          "score": 0.35
        },
        {
          "ra_id": "comp.security",
          "ra_name": "Security",
          "score": 0.35
        }
      ],
      "ground_truth": [
        {
          "ra_name": "Business_Logic_Layer",
          "ra_id": "comp.business",
          "confidence": 1,
          "source_row": 32,
          "aadl_graph_id": "AadlProjects_smartparking_vehbasesafe_impl_1.aaxl2",
          "match_mode": "global_fallback"
        },
        {
          "ra_name": "Presentation_Layer",
          "ra_id": "comp.presentation",
          "confidence": 1,
          "source_row": 32,
          "aadl_graph_id": "AadlProjects_smartparking_vehbasesafe_impl_1.aaxl2",
          "match_mode": "global_fallback"
        },
        {
          "ra_name": "Business_Logic_Layer",
          "ra_id": "comp.business",
          "confidence": 1,
          "source_row": 133,
          "aadl_graph_id": "AadlProjects_smartparking_vehbasesafe_impl_1.aaxl2",
          "match_mode": "global_fallback"
        },
        {
          "ra_name": "Presentation_Layer",
          "ra_id": "comp.presentation",
          "confidence": 1,
          "source_row": 133,
          "aadl_graph_id": "AadlProjects_smartparking_vehbasesafe_impl_1.aaxl2",
          "match_mode": "global_fallback"
        },
        {
          "ra_name": "Business_Logic_Layer",
          "ra_id": "comp.business",
          "confidence": 1,
          "source_row": 163,
          "aadl_graph_id": "AadlProjects_smartparking_vehbasesafe_impl_1.aaxl2",
          "match_mode": "global_fallback"
        },
        {
          "ra_name": "Presentation_Layer",
          "ra_id": "comp.presentation",
          "confidence": 1,
          "source_row": 163,
          "aadl_graph_id": "AadlProjects_smartparking_vehbasesafe_impl_1.aaxl2",
          "match_mode": "global_fallback"
        }
      ],
      "is_correct": true
    },
    {
      "node_id": "comp_fromdriver",
      "graph_node_id": "fromdriver::../../github/AadlProjects/smartpark/smartparking.aadl#smartparking.fromdriver.impl",
      "node_name": "fromdriver",
      "category": "thread",
      "classifier": "../../github/AadlProjects/smartpark/smartparking.aadl#smartparking.fromdriver.impl",
      "predicted_ra_id": "comp.presentation",
      "predicted_ra_name": "Presentation_Layer",
      "prediction_score": 0.553667,
      "top_5_candidates": [
        {
          "ra_id": "comp.presentation",
          "ra_name": "Presentation_Layer",
          "score": 0.553667
        },
        {
          "ra_id": "comp.data",
          "ra_name": "Data_Management_Layer",
          "score": 0.553667
        },
        {
          "ra_id": "comp.business",
          "ra_name": "Business_Logic_Layer",
          "score": 0.497667
        },
        {
          "ra_id": "comp.security",
          "ra_name": "Security",
          "score": 0.497667
        }
      ],
      "ground_truth": [
        {
          "ra_name": "Business_Logic_Layer",
          "ra_id": "comp.business",
          "confidence": 1,
          "source_row": 33,
          "aadl_graph_id": "AadlProjects_smartparking_vehbasesafe_impl_1.aaxl2",
          "match_mode": "global_fallback"
        },
        {
          "ra_name": "Business_Logic_Layer",
          "ra_id": "comp.business",
          "confidence": 1,
          "source_row": 134,
          "aadl_graph_id": "AadlProjects_smartparking_vehbasesafe_impl_1.aaxl2",
          "match_mode": "global_fallback"
        },
        {
          "ra_name": "Business_Logic_Layer",
          "ra_id": "comp.business",
          "confidence": 1,
          "source_row": 164,
          "aadl_graph_id": "AadlProjects_smartparking_vehbasesafe_impl_1.aaxl2",
          "match_mode": "global_fallback"
        }
      ],
      "is_correct": false
    },
    {
      "node_id": "comp_confirmation",
      "graph_node_id": "confirmation::../../github/AadlProjects/smartpark/smartparking.aadl#smartparking.confirmation.impl",
      "node_name": "confirmation",
      "category": "thread",
      "classifier": "../../github/AadlProjects/smartpark/smartparking.aadl#smartparking.confirmation.impl",
      "predicted_ra_id": "comp.presentation",
      "predicted_ra_name": "Presentation_Layer",
      "prediction_score": 0.553667,
      "top_5_candidates": [
        {
          "ra_id": "comp.presentation",
          "ra_name": "Presentation_Layer",
          "score": 0.553667
        },
        {
          "ra_id": "comp.data",
          "ra_name": "Data_Management_Layer",
          "score": 0.553667
        },
        {
          "ra_id": "comp.business",
          "ra_name": "Business_Logic_Layer",
          "score": 0.497667
        },
        {
          "ra_id": "comp.security",
          "ra_name": "Security",
          "score": 0.497667
        }
      ],
      "ground_truth": [
        {
          "ra_name": "Business_Logic_Layer",
          "ra_id": "comp.business",
          "confidence": 1,
          "source_row": 34,
          "aadl_graph_id": "AadlProjects_smartparking_vehbasesafe_impl_1.aaxl2",
          "match_mode": "global_fallback"
        },
        {
          "ra_name": "Business_Logic_Layer",
          "ra_id": "comp.business",
          "confidence": 1,
          "source_row": 135,
          "aadl_graph_id": "AadlProjects_smartparking_vehbasesafe_impl_1.aaxl2",
          "match_mode": "global_fallback"
        },
        {
          "ra_name": "Business_Logic_Layer",
          "ra_id": "comp.business",
          "confidence": 1,
          "source_row": 165,
          "aadl_graph_id": "AadlProjects_smartparking_vehbasesafe_impl_1.aaxl2",
          "match_mode": "global_fallback"
        }
      ],
      "is_correct": false
    },
    {
      "node_id": "comp_vehiclelocationdata",
      "graph_node_id": "vehiclelocationdata::../../github/AadlProjects/smartpark/smartparking.aadl#smartparking.vehiclelocationdata.impl",
      "node_name": "vehiclelocationdata",
      "category": "process",
      "classifier": "../../github/AadlProjects/smartpark/smartparking.aadl#smartparking.vehiclelocationdata.impl",
      "predicted_ra_id": "comp.presentation",
      "predicted_ra_name": "Presentation_Layer",
      "prediction_score": 0.364,
      "top_5_candidates": [
        {
          "ra_id": "comp.presentation",
          "ra_name": "Presentation_Layer",
          "score": 0.364
        },
        {
          "ra_id": "comp.data",
          "ra_name": "Data_Management_Layer",
          "score": 0.364
        },
        {
          "ra_id": "comp.business",
          "ra_name": "Business_Logic_Layer",
          "score": 0.308
        },
        {
          "ra_id": "comp.security",
          "ra_name": "Security",
          "score": 0.308
        }
      ],
      "ground_truth": [
        {
          "ra_name": "Business_Logic_Layer",
          "ra_id": "comp.business",
          "confidence": 1,
          "source_row": 35,
          "aadl_graph_id": "AadlProjects_smartparking_vehbasesafe_impl_1.aaxl2",
          "match_mode": "global_fallback"
        },
        {
          "ra_name": "Data_Management_Layer",
          "ra_id": "comp.data",
          "confidence": 1,
          "source_row": 35,
          "aadl_graph_id": "AadlProjects_smartparking_vehbasesafe_impl_1.aaxl2",
          "match_mode": "global_fallback"
        },
        {
          "ra_name": "Business_Logic_Layer",
          "ra_id": "comp.business",
          "confidence": 1,
          "source_row": 136,
          "aadl_graph_id": "AadlProjects_smartparking_vehbasesafe_impl_1.aaxl2",
          "match_mode": "global_fallback"
        },
        {
          "ra_name": "Data_Management_Layer",
          "ra_id": "comp.data",
          "confidence": 1,
          "source_row": 136,
          "aadl_graph_id": "AadlProjects_smartparking_vehbasesafe_impl_1.aaxl2",
          "match_mode": "global_fallback"
        },
        {
          "ra_name": "Business_Logic_Layer",
          "ra_id": "comp.business",
          "confidence": 1,
          "source_row": 166,
          "aadl_graph_id": "AadlProjects_smartparking_vehbasesafe_impl_1.aaxl2",
          "match_mode": "global_fallback"
        },
        {
          "ra_name": "Data_Management_Layer",
          "ra_id": "comp.data",
          "confidence": 1,
          "source_row": 166,
          "aadl_graph_id": "AadlProjects_smartparking_vehbasesafe_impl_1.aaxl2",
          "match_mode": "global_fallback"
        }
      ],
      "is_correct": false
    },
    {
      "node_id": "comp_vehicleloc",
      "graph_node_id": "vehicleloc::../../github/AadlProjects/smartpark/smartparking.aadl#smartparking.vehicleloc.impl",
      "node_name": "vehicleloc",
      "category": "thread",
      "classifier": "../../github/AadlProjects/smartpark/smartparking.aadl#smartparking.vehicleloc.impl",
      "predicted_ra_id": "comp.presentation",
      "predicted_ra_name": "Presentation_Layer",
      "prediction_score": 0.553667,
      "top_5_candidates": [
        {
          "ra_id": "comp.presentation",
          "ra_name": "Presentation_Layer",
          "score": 0.553667
        },
        {
          "ra_id": "comp.data",
          "ra_name": "Data_Management_Layer",
          "score": 0.553667
        },
        {
          "ra_id": "comp.business",
          "ra_name": "Business_Logic_Layer",
          "score": 0.497667
        },
        {
          "ra_id": "comp.security",
          "ra_name": "Security",
          "score": 0.497667
        }
      ],
      "ground_truth": [
        {
          "ra_name": "Business_Logic_Layer",
          "ra_id": "comp.business",
          "confidence": 1,
          "source_row": 36,
          "aadl_graph_id": "AadlProjects_smartparking_vehbasesafe_impl_1.aaxl2",
          "match_mode": "global_fallback"
        },
        {
          "ra_name": "Business_Logic_Layer",
          "ra_id": "comp.business",
          "confidence": 1,
          "source_row": 137,
          "aadl_graph_id": "AadlProjects_smartparking_vehbasesafe_impl_1.aaxl2",
          "match_mode": "global_fallback"
        },
        {
          "ra_name": "Business_Logic_Layer",
          "ra_id": "comp.business",
          "confidence": 1,
          "source_row": 167,
          "aadl_graph_id": "AadlProjects_smartparking_vehbasesafe_impl_1.aaxl2",
          "match_mode": "global_fallback"
        }
      ],
      "is_correct": false
    },
    {
      "node_id": "comp_driverinformationinterface",
      "graph_node_id": "driverinformationinterface::../../github/AadlProjects/smartpark/smartparking.aadl#smartparking.driverinformationinterface.impl",
      "node_name": "driverinformationinterface",
      "category": "process",
      "classifier": "../../github/AadlProjects/smartpark/smartparking.aadl#smartparking.driverinformationinterface.impl",
      "predicted_ra_id": "comp.presentation",
      "predicted_ra_name": "Presentation_Layer",
      "prediction_score": 0.364,
      "top_5_candidates": [
        {
          "ra_id": "comp.presentation",
          "ra_name": "Presentation_Layer",
          "score": 0.364
        },
        {
          "ra_id": "comp.data",
          "ra_name": "Data_Management_Layer",
          "score": 0.364
        },
        {
          "ra_id": "comp.business",
          "ra_name": "Business_Logic_Layer",
          "score": 0.308
        },
        {
          "ra_id": "comp.security",
          "ra_name": "Security",
          "score": 0.308
        }
      ],
      "ground_truth": [
        {
          "ra_name": "Business_Logic_Layer",
          "ra_id": "comp.business",
          "confidence": 1,
          "source_row": 37,
          "aadl_graph_id": "AadlProjects_smartparking_vehbasesafe_impl_1.aaxl2",
          "match_mode": "global_fallback"
        },
        {
          "ra_name": "Presentation_Layer",
          "ra_id": "comp.presentation",
          "confidence": 1,
          "source_row": 37,
          "aadl_graph_id": "AadlProjects_smartparking_vehbasesafe_impl_1.aaxl2",
          "match_mode": "global_fallback"
        },
        {
          "ra_name": "Business_Logic_Layer",
          "ra_id": "comp.business",
          "confidence": 1,
          "source_row": 138,
          "aadl_graph_id": "AadlProjects_smartparking_vehbasesafe_impl_1.aaxl2",
          "match_mode": "global_fallback"
        },
        {
          "ra_name": "Presentation_Layer",
          "ra_id": "comp.presentation",
          "confidence": 1,
          "source_row": 138,
          "aadl_graph_id": "AadlProjects_smartparking_vehbasesafe_impl_1.aaxl2",
          "match_mode": "global_fallback"
        },
        {
          "ra_name": "Business_Logic_Layer",
          "ra_id": "comp.business",
          "confidence": 1,
          "source_row": 168,
          "aadl_graph_id": "AadlProjects_smartparking_vehbasesafe_impl_1.aaxl2",
          "match_mode": "global_fallback"
        },
        {
          "ra_name": "Presentation_Layer",
          "ra_id": "comp.presentation",
          "confidence": 1,
          "source_row": 168,
          "aadl_graph_id": "AadlProjects_smartparking_vehbasesafe_impl_1.aaxl2",
          "match_mode": "global_fallback"
        }
      ],
      "is_correct": true
    },
    {
      "node_id": "comp_persidentity",
      "graph_node_id": "persidentity::../../github/AadlProjects/smartpark/smartparking.aadl#smartparking.persidentity.impl",
      "node_name": "persidentity",
      "category": "thread",
      "classifier": "../../github/AadlProjects/smartpark/smartparking.aadl#smartparking.persidentity.impl",
      "predicted_ra_id": "comp.presentation",
      "predicted_ra_name": "Presentation_Layer",
      "prediction_score": 0.553667,
      "top_5_candidates": [
        {
          "ra_id": "comp.presentation",
          "ra_name": "Presentation_Layer",
          "score": 0.553667
        },
        {
          "ra_id": "comp.data",
          "ra_name": "Data_Management_Layer",
          "score": 0.553667
        },
        {
          "ra_id": "comp.business",
          "ra_name": "Business_Logic_Layer",
          "score": 0.497667
        },
        {
          "ra_id": "comp.security",
          "ra_name": "Security",
          "score": 0.497667
        }
      ],
      "ground_truth": [
        {
          "ra_name": "Business_Logic_Layer",
          "ra_id": "comp.business",
          "confidence": 1,
          "source_row": 38,
          "aadl_graph_id": "AadlProjects_smartparking_vehbasesafe_impl_1.aaxl2",
          "match_mode": "global_fallback"
        },
        {
          "ra_name": "Business_Logic_Layer",
          "ra_id": "comp.business",
          "confidence": 1,
          "source_row": 139,
          "aadl_graph_id": "AadlProjects_smartparking_vehbasesafe_impl_1.aaxl2",
          "match_mode": "global_fallback"
        },
        {
          "ra_name": "Business_Logic_Layer",
          "ra_id": "comp.business",
          "confidence": 1,
          "source_row": 169,
          "aadl_graph_id": "AadlProjects_smartparking_vehbasesafe_impl_1.aaxl2",
          "match_mode": "global_fallback"
        }
      ],
      "is_correct": false
    }
  ],
  "runtime_seconds": 0.000719
}